{
  "type": "FeatureCollection",
  "features": [
    {
      "type": "Feature",
      "properties": {
        "name": "Dandelion Seed"
      },
      "geometry": {
        "type": "Point",
        "coordinates": [
          75.19043,
          64.997939
        ]
      }
    },
    {
      "type": "Feature",
      "properties": {
        "name": "Dandelion Seed"
      },
      "geometry": {
        "type": "Point",
        "coordinates": [
          75.234375,
          64.811557
        ]
      }
    },
    {
      "type": "Feature",
      "properties": {
        "name": "Dandelion Seed"
      },
      "geometry": {
        "type": "Point",
        "coordinates": [
          74.443359,
          64.71788
        ]
      }
    },
    {
      "type": "Feature",
      "properties": {
        "name": "Dandelion Seed"
      },
      "geometry": {
        "type": "Point",
        "coordinates": [
          55.942383,
          56.535258
        ]
      }
    },
    {
      "type": "Feature",
      "properties": {
        "name": "Dandelion Seed"
      },
      "geometry": {
        "type": "Point",
        "coordinates": [
          55.458984,
          56.46249
        ]
      }
    },
    {
      "type": "Feature",
      "properties": {
        "name": "Dandelion Seed"
      },
      "geometry": {
        "type": "Point",
        "coordinates": [
          55.195313,
          56.0475
        ]
      }
    },
    {
      "type": "Feature",
      "properties": {
        "name": "Dandelion Seed"
      },
      "geometry": {
        "type": "Point",
        "coordinates": [
          57.041016,
          57.468589
        ]
      }
    },
    {
      "type": "Feature",
      "properties": {
        "name": "Dandelion Seed"
      },
      "geometry": {
        "type": "Point",
        "coordinates": [
          57.480469,
          57.704147
        ]
      }
    },
    {
      "type": "Feature",
      "properties": {
        "name": "Dandelion Seed"
      },
      "geometry": {
        "type": "Point",
        "coordinates": [
          56.99707,
          57.868132
        ]
      }
    },
    {
      "type": "Feature",
      "properties": {
        "name": "Dandelion Seed"
      },
      "geometry": {
        "type": "Point",
        "coordinates": [
          57.216797,
          58.147519
        ]
      }
    },
    {
      "type": "Feature",
      "properties": {
        "name": "Dandelion Seed"
      },
      "geometry": {
        "type": "Point",
        "coordinates": [
          56.733398,
          60.305185
        ]
      }
    },
    {
      "type": "Feature",
      "properties": {
        "name": "Dandelion Seed"
      },
      "geometry": {
        "type": "Point",
        "coordinates": [
          52.866211,
          61.689872
        ]
      }
    },
    {
      "type": "Feature",
      "properties": {
        "name": "Dandelion Seed"
      },
      "geometry": {
        "type": "Point",
        "coordinates": [
          22.324219,
          51.727028
        ]
      }
    }
  ]
}